Metadata-Version: 2.1
Name: abletondrumrack
Version: 1.0.1
Summary: Create Ableton Live 11 Drum Rack presets.
Home-page: UNKNOWN
Author: Daniel Kavoulakos
Author-email: dan_kavoulakos@hotmail.com
License: MIT
Platform: UNKNOWN
Requires-Python: >=3.7
License-File: LICENSE
